curdrice/__init__.py
curdrice/app.py
curdrice/main.py
curdrice/models.py
curdrice/test.py
curdrice_v2-0.1.dist-info/LICENSE
curdrice_v2-0.1.dist-info/METADATA
curdrice_v2-0.1.dist-info/WHEEL
curdrice_v2-0.1.dist-info/entry_points.txt
curdrice_v2-0.1.dist-info/top_level.txt
curdrice_v2-0.1.dist-info/RECORD
