Metadata-Version: 2.1
Name: curdrice-v2
Version: 0.1
Summary: A ML model training automation tool
License: MIT
Classifier: Programming Language :: Python :: 3
Classifier: Operating System :: OS Independent
Classifier: License :: OSI Approved :: MIT License
License-File: LICENSE
Requires-Dist: click
Requires-Dist: numpy
Requires-Dist: pandas
Requires-Dist: scikit-learn
Requires-Dist: openpyxl
Requires-Dist: scikit-learn-extra
Requires-Dist: mlxtend
Requires-Dist: joblib
Requires-Dist: tabulate
